setup.py
test_pypi/__init__.py
test_pypi/text.py
test_pypi.egg-info/PKG-INFO
test_pypi.egg-info/SOURCES.txt
test_pypi.egg-info/dependency_links.txt
test_pypi.egg-info/not-zip-safe
test_pypi.egg-info/requires.txt
test_pypi.egg-info/top_level.txt