Metadata-Version: 1.0
Name: test-pypi
Version: 0.22
Summary: Test project to learn how pypi works
Home-page: UNKNOWN
Author: Emiliano G. Molina
Author-email: emiliano.g.molina@gmail.com
License: MIT
Platform: UNKNOWN
